MANIFEST.in
README.md
requirements.txt
setup.py
cms/__init__.py
cms/bin/__init__.py
cms/bin/main.py
cms/conf/cms.config.xlsx
cms/conf/cms.config.yuhuan.xlsx
cms/util/__init__.py
cms/util/cms/__init__.py
cms/util/cms/project.py
cms/util/cms/title.py
cms/util/lims/__init__.py
cms/util/lims/lims.py
cms/util/lims/lims_wsdl.py
cms/util/report/__init__.py
cms/util/report/report.py
cms/util/settlement/__init__.py
cms/util/settlement/settlement.py
cms/util/settlement/title.py
novo_cms.egg-info/PKG-INFO
novo_cms.egg-info/SOURCES.txt
novo_cms.egg-info/dependency_links.txt
novo_cms.egg-info/entry_points.txt
novo_cms.egg-info/requires.txt
novo_cms.egg-info/top_level.txt