Metadata-Version: 2.1
Name: novo-cms
Version: 1.0.13
Summary: CMS Crawler for Novogene
Home-page: https://github.com/suqingdong/cms
Author: suqingdong
Author-email: suqingdong@novogene.com
License: BSD License
Platform: UNKNOWN
Classifier: Development Status :: 5 - Production/Stable
Classifier: Operating System :: OS Independent
Classifier: Intended Audience :: Developers
Classifier: License :: OSI Approved :: BSD License
Classifier: Programming Language :: Python
Classifier: Programming Language :: Python :: 2
Classifier: Programming Language :: Python :: 2.7
Classifier: Topic :: Software Development :: Libraries
